mcp_mikrotik/__init__.py
mcp_mikrotik/connector.py
mcp_mikrotik/logger.py
mcp_mikrotik/mikrotik_ssh_client.py
mcp_mikrotik/serve.py
mcp_mikrotik/server.py
mcp_mikrotik/scope/__init__.py
mcp_mikrotik/scope/backup.py
mcp_mikrotik/scope/dhcp.py
mcp_mikrotik/scope/dns.py
mcp_mikrotik/scope/firewall_filter.py
mcp_mikrotik/scope/firewall_nat.py
mcp_mikrotik/scope/ip_address.py
mcp_mikrotik/scope/ip_pool.py
mcp_mikrotik/scope/logs.py
mcp_mikrotik/scope/routes.py
mcp_mikrotik/scope/users.py
mcp_mikrotik/scope/vlan.py
mcp_mikrotik/scope/wireless.py
mcp_mikrotik/settings/__init__.py
mcp_mikrotik/settings/configuration.py
mcp_mikrotik/tools/__init__.py
mcp_mikrotik/tools/backup_tools.py
mcp_mikrotik/tools/dhcp_tools.py
mcp_mikrotik/tools/dns_tools.py
mcp_mikrotik/tools/firewall_tools.py
mcp_mikrotik/tools/ip_tools.py
mcp_mikrotik/tools/log_tools.py
mcp_mikrotik/tools/route_tools.py
mcp_mikrotik/tools/tool_registry.py
mcp_mikrotik/tools/user_tools.py
mcp_mikrotik/tools/vlan_tools.py
mcp_mikrotik/tools/wireless_tools.py
mcp_server_mikrotik-0.2.0.post28.dist-info/licenses/LICENSE
mcp_server_mikrotik-0.2.0.post28.dist-info/METADATA
mcp_server_mikrotik-0.2.0.post28.dist-info/WHEEL
mcp_server_mikrotik-0.2.0.post28.dist-info/entry_points.txt
mcp_server_mikrotik-0.2.0.post28.dist-info/top_level.txt
mcp_server_mikrotik-0.2.0.post28.dist-info/RECORD
