Metadata-Version: 2.4
Name: mcp-server-mikrotik
Version: 0.2.0.post28
Summary: MCP server for MikroTik integration with Claude and other AI assistants
Author-email: Jeff Nasseri <sir.jeff.nasseri@gmail.com>
License: MIT
Project-URL: Homepage, https://github.com/jeff-nasseri/mikrotik-mcp
Project-URL: Issues, https://github.com/jeff-nasseri/mikrotik-mcp/issues
Project-URL: Repository, https://github.com/jeff-nasseri/mikrotik-mcp
Keywords: mcp,mikrotik,router,network,ai,assistant
Classifier: Programming Language :: Python :: 3
Classifier: Programming Language :: Python :: 3.8
Classifier: Programming Language :: Python :: 3.9
Classifier: Programming Language :: Python :: 3.10
Classifier: Programming Language :: Python :: 3.11
Classifier: License :: OSI Approved :: MIT License
Classifier: Operating System :: OS Independent
Classifier: Intended Audience :: Developers
Classifier: Topic :: System :: Networking
Requires-Python: >=3.8
License-File: LICENSE
Requires-Dist: mcp>=1.8.0
Requires-Dist: paramiko>=3.5.1
Requires-Dist: pydantic>=2.11.4
Requires-Dist: pydantic-settings>=2.9.1
Requires-Dist: python-dotenv>=1.1.0
Dynamic: license-file
